{
  "mpn": "HTG-K800",
  "name": "HTG-K800",
  "status": "active",
  "url": "http://www.hitechglobal.com/boards/kintex-ultrascale.htm",
  "vendor": "hitech-global",
  "price": {
    "value": 4995,
    "currency": "USD"
  },
  "device": {
    "part": "XCKU115-2FLVA1517E",
    "vendor": "amd-xilinx"
  },
  "memory": [
    {
      "type": "DDR4",
      "size_mb": 2560,
      "width_bits": 72,
      "ecc": true
    }
  ],
  "flash": [
    {
      "type": "QSPI",
      "size_mb": 32
    }
  ],
  "clocking": {
    "programmable": true
  },
  "pcie": [
    {
      "type": "Edge",
      "lanes": 8,
      "gen": 3
    }
  ],
  "usb_bridge": [
    {
      "connector": "Mini-B",
      "functions": [
        "uart"
      ]
    }
  ],
  "expansion": {
    "fmc": [
      {
        "slot": "HPC0",
        "type": "hpc"
      },
      {
        "slot": "HPC1",
        "type": "hpc"
      }
    ]
  }
}
