{
  "mpn": "TE0821-02-3BE81ML",
  "name": "TE0821 \u2014 ZU3EG-1E, 2 GB DDR4",
  "status": "active",
  "url": "https://www.trenz-electronic.de/en/MPSoC-Module-with-AMD-Zynq-UltraScale-ZU3EG-1E-2-GByte-DDR4-low-profile/TE0821-02-3BE81ML",
  "vendor": "trenz",
  "price": {
    "value": 646.86,
    "currency": "USD"
  },
  "device": {
    "part": "XCZU3EG-1SFVC784E",
    "vendor": "amd-xilinx"
  },
  "memory": [
    {
      "type": "DDR4",
      "size_mb": 2048
    }
  ],
  "flash": [
    {
      "type": "QSPI",
      "size_mb": 128
    },
    {
      "type": "eMMC",
      "size_mb": 8192
    },
    {
      "type": "SPI",
      "size_mb": 64
    }
  ]
}
